LICENSE
aiohttp_client_request/__init__.py
aiohttp_client_request/py.typed
aiohttp_client_request-0.1.2.dist-info/LICENSE
aiohttp_client_request-0.1.2.dist-info/METADATA
aiohttp_client_request-0.1.2.dist-info/WHEEL
aiohttp_client_request-0.1.2.dist-info/RECORD
