Metadata-Version: 2.1
Name: aiohttp_client_request
Version: 0.1.2
Summary: aiohttp request extension.
Home-page: https://github.com/ChenyangGao/python-modules/tree/main/aiohttp_client_request
License: MIT
Keywords: aiohttp,request
Author: ChenyangGao
Author-email: wosiwujm@gmail.com
Requires-Python: >=3.12,<4.0
Classifier: Development Status :: 5 - Production/Stable
Classifier: Intended Audience :: Developers
Classifier: License :: OSI Approved :: MIT License
Classifier: Operating System :: OS Independent
Classifier: Programming Language :: Python
Classifier: Programming Language :: Python :: 3
Classifier: Programming Language :: Python :: 3.12
Classifier: Programming Language :: Python :: 3.13
Classifier: Programming Language :: Python :: 3 :: Only
Classifier: Topic :: Software Development
Classifier: Topic :: Software Development :: Libraries
Classifier: Topic :: Software Development :: Libraries :: Python Modules
Requires-Dist: aiohttp
Requires-Dist: http_response (>=0.0.9)
Requires-Dist: python-argtools (>=0.0.2)
Requires-Dist: python-cookietools (>=0.1.2)
Requires-Dist: python-dicttools (>=0.0.4)
Requires-Dist: python-filewrap (>=0.2.8)
Requires-Dist: python-http_request (>=0.1.4)
Requires-Dist: python-undefined (>=0.0.3)
Requires-Dist: yarl
Project-URL: Repository, https://github.com/ChenyangGao/python-modules/tree/main/aiohttp_client_request
